{
    "version": "0.9.3",
    "generated": "18/05/2022 9:58:31 AM",
    "resolution": {
        "width": 240,
        "height": 180
    },
    "depth": 4,
    "width": 4,
    "layers": [
        {
            "id": 1,
            "name": "ceiling",
            "mode": 2,
            "type": 0,
            "tiles": [
                {
                    "type": "ceiling",
                    "tile": {
                        "x": -4,
                        "y": -4
                    },
                    "screen": {
                        "x": 234,
                        "y": 56
                    },
                    "coords": {
                        "x": 309,
                        "y": 396,
                        "w": 6,
                        "h": 1
                    }
                },
                {
                    "type": "ceiling",
                    "tile": {
                        "x": -3,
                        "y": -4
                    },
                    "screen": {
                        "x": 202,
                        "y": 53
                    },
                    "coords": {
                        "x": 181,
                        "y": 102,
                        "w": 38,
                        "h": 4
                    }
                },
                {
                    "type": "ceiling",
                    "tile": {
                        "x": -3,
                        "y": -3
                    },
                    "screen": {
                        "x": 227,
                        "y": 50
                    },
                    "coords": {
                        "x": 309,
                        "y": 400,
                        "w": 13,
                        "h": 3
                    }
                },
                {
                    "type": "ceiling",
                    "tile": {
                        "x": -2,
                        "y": -4
                    },
                    "screen": {
                        "x": 169,
                        "y": 53
                    },
                    "coords": {
                        "x": 224,
                        "y": 254,
                        "w": 51,
                        "h": 4
                    }
                },
                {
                    "type": "ceiling",
                    "tile": {
                        "x": -2,
                        "y": -3
                    },
                    "screen": {
                        "x": 184,
                        "y": 48
                    },
                    "coords": {
                        "x": 399,
                        "y": 272,
                        "w": 56,
                        "h": 5
                    }
                },
                {
                    "type": "ceiling",
                    "tile": {
                        "x": -2,
                        "y": -2
                    },
                    "screen": {
                        "x": 203,
                        "y": 38
                    },
                    "coords": {
                        "x": 373,
                        "y": 350,
                        "w": 37,
                        "h": 10
                    }
                },
                {
                    "type": "ceiling",
                    "tile": {
                        "x": -1,
                        "y": -4
                    },
                    "screen": {
                        "x": 136,
                        "y": 53
                    },
                    "coords": {
                        "x": 463,
                        "y": 301,
                        "w": 44,
                        "h": 4
                    }
                },
                {
                    "type": "ceiling",
                    "tile": {
                        "x": -1,
                        "y": -3
                    },
                    "screen": {
                        "x": 141,
                        "y": 48
                    },
                    "coords": {
                        "x": 403,
                        "y": 280,
                        "w": 58,
                        "h": 5
                    }
                },
                {
                    "type": "ceiling",
                    "tile": {
                        "x": -1,
                        "y": -2
                    },
                    "screen": {
                        "x": 148,
                        "y": 37
                    },
                    "coords": {
                        "x": 369,
                        "y": 317,
                        "w": 92,
                        "h": 11
                    }
                },
                {
                    "type": "ceiling",
                    "tile": {
                        "x": -1,
                        "y": -1
                    },
                    "screen": {
                        "x": 161,
                        "y": 5
                    },
                    "coords": {
                        "x": 42,
                        "y": 14,
                        "w": 79,
                        "h": 32
                    }
                },
                {
                    "type": "ceiling",
                    "tile": {
                        "x": -1,
                        "y": 0
                    },
                    "screen": {
                        "x": 201,
                        "y": 0
                    },
                    "coords": {
                        "x": 124,
                        "y": 4,
                        "w": 39,
                        "h": 5
                    }
                },
                {
                    "type": "ceiling",
                    "tile": {
                        "x": 0,
                        "y": -4
                    },
                    "screen": {
                        "x": 100,
                        "y": 53
                    },
                    "coords": {
                        "x": 181,
                        "y": 116,
                        "w": 40,
                        "h": 4
                    }
                },
                {
                    "type": "ceiling",
                    "tile": {
                        "x": 0,
                        "y": -3
                    },
                    "screen": {
                        "x": 94,
                        "y": 48
                    },
                    "coords": {
                        "x": 458,
                        "y": 272,
                        "w": 52,
                        "h": 5
                    }
                },
                {
                    "type": "ceiling",
                    "tile": {
                        "x": 0,
                        "y": -2
                    },
                    "screen": {
                        "x": 80,
                        "y": 37
                    },
                    "coords": {
                        "x": 320,
                        "y": 285,
                        "w": 80,
                        "h": 11
                    }
                },
                {
                    "type": "ceiling",
                    "tile": {
                        "x": 0,
                        "y": -1
                    },
                    "screen": {
                        "x": 40,
                        "y": 5
                    },
                    "coords": {
                        "x": 124,
                        "y": 315,
                        "w": 160,
                        "h": 32
                    }
                },
                {
                    "type": "ceiling",
                    "tile": {
                        "x": 0,
                        "y": 0
                    },
                    "screen": {
                        "x": 34,
                        "y": 0
                    },
                    "coords": {
                        "x": 224,
                        "y": 272,
                        "w": 172,
                        "h": 5
                    }
                },
                {
                    "type": "ceiling",
                    "tile": {
                        "x": 1,
                        "y": -4
                    },
                    "screen": {
                        "x": 60,
                        "y": 53
                    },
                    "coords": {
                        "x": 463,
                        "y": 308,
                        "w": 44,
                        "h": 4
                    }
                },
                {
                    "type": "ceiling",
                    "tile": {
                        "x": 1,
                        "y": -3
                    },
                    "screen": {
                        "x": 41,
                        "y": 48
                    },
                    "coords": {
                        "x": 165,
                        "y": 352,
                        "w": 58,
                        "h": 5
                    }
                },
                {
                    "type": "ceiling",
                    "tile": {
                        "x": 1,
                        "y": -2
                    },
                    "screen": {
                        "x": 0,
                        "y": 37
                    },
                    "coords": {
                        "x": 368,
                        "y": 301,
                        "w": 92,
                        "h": 11
                    }
                },
                {
                    "type": "ceiling",
                    "tile": {
                        "x": 1,
                        "y": -1
                    },
                    "screen": {
                        "x": 0,
                        "y": 5
                    },
                    "coords": {
                        "x": 287,
                        "y": 315,
                        "w": 79,
                        "h": 32
                    }
                },
                {
                    "type": "ceiling",
                    "tile": {
                        "x": 1,
                        "y": 0
                    },
                    "screen": {
                        "x": 0,
                        "y": 0
                    },
                    "coords": {
                        "x": 465,
                        "y": 318,
                        "w": 39,
                        "h": 5
                    }
                },
                {
                    "type": "ceiling",
                    "tile": {
                        "x": 2,
                        "y": -4
                    },
                    "screen": {
                        "x": 20,
                        "y": 53
                    },
                    "coords": {
                        "x": 452,
                        "y": 265,
                        "w": 51,
                        "h": 4
                    }
                },
                {
                    "type": "ceiling",
                    "tile": {
                        "x": 2,
                        "y": -3
                    },
                    "screen": {
                        "x": 0,
                        "y": 48
                    },
                    "coords": {
                        "x": 455,
                        "y": 355,
                        "w": 56,
                        "h": 5
                    }
                },
                {
                    "type": "ceiling",
                    "tile": {
                        "x": 2,
                        "y": -2
                    },
                    "screen": {
                        "x": 0,
                        "y": 38
                    },
                    "coords": {
                        "x": 250,
                        "y": 350,
                        "w": 37,
                        "h": 10
                    }
                },
                {
                    "type": "ceiling",
                    "tile": {
                        "x": 3,
                        "y": -4
                    },
                    "screen": {
                        "x": 0,
                        "y": 53
                    },
                    "coords": {
                        "x": 181,
                        "y": 109,
                        "w": 38,
                        "h": 4
                    }
                },
                {
                    "type": "ceiling",
                    "tile": {
                        "x": 3,
                        "y": -3
                    },
                    "screen": {
                        "x": 0,
                        "y": 50
                    },
                    "coords": {
                        "x": 309,
                        "y": 406,
                        "w": 13,
                        "h": 3
                    }
                }
            ]
        },
        {
            "id": 2,
            "name": "ground",
            "mode": 2,
            "type": 0,
            "tiles": [
                {
                    "type": "ground",
                    "tile": {
                        "x": -4,
                        "y": -4
                    },
                    "screen": {
                        "x": 236,
                        "y": 89
                    },
                    "coords": {
                        "x": 318,
                        "y": 396,
                        "w": 4,
                        "h": 1
                    }
                },
                {
                    "type": "ground",
                    "tile": {
                        "x": -3,
                        "y": -4
                    },
                    "screen": {
                        "x": 203,
                        "y": 89
                    },
                    "coords": {
                        "x": 455,
                        "y": 432,
                        "w": 37,
                        "h": 5
                    }
                },
                {
                    "type": "ground",
                    "tile": {
                        "x": -3,
                        "y": -3
                    },
                    "screen": {
                        "x": 224,
                        "y": 94
                    },
                    "coords": {
                        "x": 309,
                        "y": 412,
                        "w": 16,
                        "h": 4
                    }
                },
                {
                    "type": "ground",
                    "tile": {
                        "x": -2,
                        "y": -4
                    },
                    "screen": {
                        "x": 170,
                        "y": 89
                    },
                    "coords": {
                        "x": 346,
                        "y": 264,
                        "w": 50,
                        "h": 5
                    }
                },
                {
                    "type": "ground",
                    "tile": {
                        "x": -2,
                        "y": -3
                    },
                    "screen": {
                        "x": 182,
                        "y": 94
                    },
                    "coords": {
                        "x": 224,
                        "y": 261,
                        "w": 58,
                        "h": 8
                    }
                },
                {
                    "type": "ground",
                    "tile": {
                        "x": -2,
                        "y": -2
                    },
                    "screen": {
                        "x": 202,
                        "y": 102
                    },
                    "coords": {
                        "x": 455,
                        "y": 440,
                        "w": 38,
                        "h": 15
                    }
                },
                {
                    "type": "ground",
                    "tile": {
                        "x": -1,
                        "y": -4
                    },
                    "screen": {
                        "x": 137,
                        "y": 89
                    },
                    "coords": {
                        "x": 465,
                        "y": 334,
                        "w": 43,
                        "h": 5
                    }
                },
                {
                    "type": "ground",
                    "tile": {
                        "x": -1,
                        "y": -3
                    },
                    "screen": {
                        "x": 141,
                        "y": 94
                    },
                    "coords": {
                        "x": 42,
                        "y": 3,
                        "w": 59,
                        "h": 8
                    }
                },
                {
                    "type": "ground",
                    "tile": {
                        "x": -1,
                        "y": -2
                    },
                    "screen": {
                        "x": 147,
                        "y": 102
                    },
                    "coords": {
                        "x": 224,
                        "y": 280,
                        "w": 93,
                        "h": 16
                    }
                },
                {
                    "type": "ground",
                    "tile": {
                        "x": -1,
                        "y": -1
                    },
                    "screen": {
                        "x": 161,
                        "y": 118
                    },
                    "coords": {
                        "x": 373,
                        "y": 379,
                        "w": 79,
                        "h": 49
                    }
                },
                {
                    "type": "ground",
                    "tile": {
                        "x": -1,
                        "y": 0
                    },
                    "screen": {
                        "x": 202,
                        "y": 167
                    },
                    "coords": {
                        "x": 414,
                        "y": 363,
                        "w": 38,
                        "h": 13
                    }
                },
                {
                    "type": "ground",
                    "tile": {
                        "x": 0,
                        "y": -4
                    },
                    "screen": {
                        "x": 100,
                        "y": 89
                    },
                    "coords": {
                        "x": 465,
                        "y": 326,
                        "w": 40,
                        "h": 5
                    }
                },
                {
                    "type": "ground",
                    "tile": {
                        "x": 0,
                        "y": -3
                    },
                    "screen": {
                        "x": 93,
                        "y": 94
                    },
                    "coords": {
                        "x": 455,
                        "y": 363,
                        "w": 54,
                        "h": 8
                    }
                },
                {
                    "type": "ground",
                    "tile": {
                        "x": 0,
                        "y": -2
                    },
                    "screen": {
                        "x": 80,
                        "y": 102
                    },
                    "coords": {
                        "x": 165,
                        "y": 360,
                        "w": 80,
                        "h": 16
                    }
                },
                {
                    "type": "ground",
                    "tile": {
                        "x": 0,
                        "y": -1
                    },
                    "screen": {
                        "x": 39,
                        "y": 118
                    },
                    "coords": {
                        "x": 165,
                        "y": 463,
                        "w": 162,
                        "h": 49
                    }
                },
                {
                    "type": "ground",
                    "tile": {
                        "x": 0,
                        "y": 0
                    },
                    "screen": {
                        "x": 28,
                        "y": 167
                    },
                    "coords": {
                        "x": 181,
                        "y": 299,
                        "w": 184,
                        "h": 13
                    }
                },
                {
                    "type": "ground",
                    "tile": {
                        "x": 1,
                        "y": -4
                    },
                    "screen": {
                        "x": 60,
                        "y": 89
                    },
                    "coords": {
                        "x": 465,
                        "y": 342,
                        "w": 43,
                        "h": 5
                    }
                },
                {
                    "type": "ground",
                    "tile": {
                        "x": 1,
                        "y": -3
                    },
                    "screen": {
                        "x": 40,
                        "y": 94
                    },
                    "coords": {
                        "x": 403,
                        "y": 288,
                        "w": 59,
                        "h": 8
                    }
                },
                {
                    "type": "ground",
                    "tile": {
                        "x": 1,
                        "y": -2
                    },
                    "screen": {
                        "x": 0,
                        "y": 102
                    },
                    "coords": {
                        "x": 369,
                        "y": 331,
                        "w": 93,
                        "h": 16
                    }
                },
                {
                    "type": "ground",
                    "tile": {
                        "x": 1,
                        "y": -1
                    },
                    "screen": {
                        "x": 0,
                        "y": 118
                    },
                    "coords": {
                        "x": 42,
                        "y": 49,
                        "w": 79,
                        "h": 49
                    }
                },
                {
                    "type": "ground",
                    "tile": {
                        "x": 1,
                        "y": 0
                    },
                    "screen": {
                        "x": 0,
                        "y": 167
                    },
                    "coords": {
                        "x": 373,
                        "y": 363,
                        "w": 38,
                        "h": 13
                    }
                },
                {
                    "type": "ground",
                    "tile": {
                        "x": 2,
                        "y": -4
                    },
                    "screen": {
                        "x": 20,
                        "y": 89
                    },
                    "coords": {
                        "x": 399,
                        "y": 264,
                        "w": 50,
                        "h": 5
                    }
                },
                {
                    "type": "ground",
                    "tile": {
                        "x": 2,
                        "y": -3
                    },
                    "screen": {
                        "x": 0,
                        "y": 94
                    },
                    "coords": {
                        "x": 285,
                        "y": 261,
                        "w": 58,
                        "h": 8
                    }
                },
                {
                    "type": "ground",
                    "tile": {
                        "x": 2,
                        "y": -2
                    },
                    "screen": {
                        "x": 0,
                        "y": 102
                    },
                    "coords": {
                        "x": 250,
                        "y": 363,
                        "w": 38,
                        "h": 15
                    }
                },
                {
                    "type": "ground",
                    "tile": {
                        "x": 3,
                        "y": -4
                    },
                    "screen": {
                        "x": 0,
                        "y": 89
                    },
                    "coords": {
                        "x": 414,
                        "y": 355,
                        "w": 37,
                        "h": 5
                    }
                },
                {
                    "type": "ground",
                    "tile": {
                        "x": 3,
                        "y": -3
                    },
                    "screen": {
                        "x": 0,
                        "y": 94
                    },
                    "coords": {
                        "x": 226,
                        "y": 353,
                        "w": 16,
                        "h": 4
                    }
                }
            ]
        },
        {
            "id": 3,
            "name": "wall",
            "mode": 2,
            "type": 0,
            "tiles": [
                {
                    "type": "front",
                    "tile": {
                        "x": -3,
                        "y": -4
                    },
                    "screen": {
                        "x": 221,
                        "y": 53
                    },
                    "coords": {
                        "x": 181,
                        "y": 167,
                        "w": 19,
                        "h": 41
                    }
                },
                {
                    "type": "front",
                    "tile": {
                        "x": -2,
                        "y": -4
                    },
                    "screen": {
                        "x": 181,
                        "y": 53
                    },
                    "coords": {
                        "x": 181,
                        "y": 255,
                        "w": 40,
                        "h": 41
                    }
                },
                {
                    "type": "front",
                    "tile": {
                        "x": -2,
                        "y": -3
                    },
                    "screen": {
                        "x": 201,
                        "y": 48
                    },
                    "coords": {
                        "x": 124,
                        "y": 144,
                        "w": 39,
                        "h": 54
                    }
                },
                {
                    "type": "front",
                    "tile": {
                        "x": -1,
                        "y": -4
                    },
                    "screen": {
                        "x": 140,
                        "y": 53
                    },
                    "coords": {
                        "x": 124,
                        "y": 56,
                        "w": 41,
                        "h": 41
                    }
                },
                {
                    "type": "front",
                    "tile": {
                        "x": -1,
                        "y": -3
                    },
                    "screen": {
                        "x": 147,
                        "y": 48
                    },
                    "coords": {
                        "x": 455,
                        "y": 458,
                        "w": 54,
                        "h": 54
                    }
                },
                {
                    "type": "front",
                    "tile": {
                        "x": -1,
                        "y": -2
                    },
                    "screen": {
                        "x": 161,
                        "y": 37
                    },
                    "coords": {
                        "x": 42,
                        "y": 266,
                        "w": 79,
                        "h": 81
                    }
                },
                {
                    "type": "front",
                    "tile": {
                        "x": -1,
                        "y": -1
                    },
                    "screen": {
                        "x": 201,
                        "y": 5
                    },
                    "coords": {
                        "x": 42,
                        "y": 101,
                        "w": 39,
                        "h": 162
                    }
                },
                {
                    "type": "front",
                    "tile": {
                        "x": 0,
                        "y": -4
                    },
                    "screen": {
                        "x": 100,
                        "y": 53
                    },
                    "coords": {
                        "x": 124,
                        "y": 12,
                        "w": 40,
                        "h": 41
                    }
                },
                {
                    "type": "front",
                    "tile": {
                        "x": 0,
                        "y": -3
                    },
                    "screen": {
                        "x": 93,
                        "y": 48
                    },
                    "coords": {
                        "x": 124,
                        "y": 258,
                        "w": 54,
                        "h": 54
                    }
                },
                {
                    "type": "front",
                    "tile": {
                        "x": 0,
                        "y": -2
                    },
                    "screen": {
                        "x": 79,
                        "y": 37
                    },
                    "coords": {
                        "x": 165,
                        "y": 379,
                        "w": 82,
                        "h": 81
                    }
                },
                {
                    "type": "front",
                    "tile": {
                        "x": 0,
                        "y": -1
                    },
                    "screen": {
                        "x": 39,
                        "y": 5
                    },
                    "coords": {
                        "x": 0,
                        "y": 350,
                        "w": 162,
                        "h": 162
                    }
                },
                {
                    "type": "front",
                    "tile": {
                        "x": 1,
                        "y": -4
                    },
                    "screen": {
                        "x": 59,
                        "y": 53
                    },
                    "coords": {
                        "x": 124,
                        "y": 100,
                        "w": 41,
                        "h": 41
                    }
                },
                {
                    "type": "side",
                    "tile": {
                        "x": 1,
                        "y": -4
                    },
                    "screen": {
                        "x": 100,
                        "y": 54
                    },
                    "coords": {
                        "x": 117,
                        "y": 224,
                        "w": 4,
                        "h": 39
                    }
                },
                {
                    "type": "front",
                    "tile": {
                        "x": 1,
                        "y": -3
                    },
                    "screen": {
                        "x": 39,
                        "y": 48
                    },
                    "coords": {
                        "x": 455,
                        "y": 374,
                        "w": 54,
                        "h": 54
                    }
                },
                {
                    "type": "side",
                    "tile": {
                        "x": 1,
                        "y": -3
                    },
                    "screen": {
                        "x": 93,
                        "y": 48
                    },
                    "coords": {
                        "x": 107,
                        "y": 210,
                        "w": 7,
                        "h": 53
                    }
                },
                {
                    "type": "front",
                    "tile": {
                        "x": 1,
                        "y": -2
                    },
                    "screen": {
                        "x": 0,
                        "y": 37
                    },
                    "coords": {
                        "x": 373,
                        "y": 431,
                        "w": 79,
                        "h": 81
                    }
                },
                {
                    "type": "side",
                    "tile": {
                        "x": 1,
                        "y": -2
                    },
                    "screen": {
                        "x": 79,
                        "y": 37
                    },
                    "coords": {
                        "x": 292,
                        "y": 379,
                        "w": 14,
                        "h": 81
                    }
                },
                {
                    "type": "front",
                    "tile": {
                        "x": 1,
                        "y": -1
                    },
                    "screen": {
                        "x": 0,
                        "y": 5
                    },
                    "coords": {
                        "x": 0,
                        "y": 2,
                        "w": 39,
                        "h": 162
                    }
                },
                {
                    "type": "side",
                    "tile": {
                        "x": 1,
                        "y": -1
                    },
                    "screen": {
                        "x": 39,
                        "y": 5
                    },
                    "coords": {
                        "x": 330,
                        "y": 351,
                        "w": 40,
                        "h": 161
                    }
                },
                {
                    "type": "side",
                    "tile": {
                        "x": 1,
                        "y": 0
                    },
                    "screen": {
                        "x": 0,
                        "y": 0
                    },
                    "coords": {
                        "x": 0,
                        "y": 167,
                        "w": 39,
                        "h": 180
                    }
                },
                {
                    "type": "front",
                    "tile": {
                        "x": 2,
                        "y": -4
                    },
                    "screen": {
                        "x": 19,
                        "y": 53
                    },
                    "coords": {
                        "x": 181,
                        "y": 211,
                        "w": 40,
                        "h": 41
                    }
                },
                {
                    "type": "side",
                    "tile": {
                        "x": 2,
                        "y": -4
                    },
                    "screen": {
                        "x": 59,
                        "y": 53
                    },
                    "coords": {
                        "x": 309,
                        "y": 419,
                        "w": 12,
                        "h": 41
                    }
                },
                {
                    "type": "front",
                    "tile": {
                        "x": 2,
                        "y": -3
                    },
                    "screen": {
                        "x": 0,
                        "y": 48
                    },
                    "coords": {
                        "x": 124,
                        "y": 201,
                        "w": 39,
                        "h": 54
                    }
                },
                {
                    "type": "side",
                    "tile": {
                        "x": 2,
                        "y": -3
                    },
                    "screen": {
                        "x": 39,
                        "y": 48
                    },
                    "coords": {
                        "x": 84,
                        "y": 209,
                        "w": 20,
                        "h": 54
                    }
                },
                {
                    "type": "side",
                    "tile": {
                        "x": 2,
                        "y": -2
                    },
                    "screen": {
                        "x": 0,
                        "y": 38
                    },
                    "coords": {
                        "x": 250,
                        "y": 381,
                        "w": 39,
                        "h": 79
                    }
                },
                {
                    "type": "front",
                    "tile": {
                        "x": 3,
                        "y": -4
                    },
                    "screen": {
                        "x": 0,
                        "y": 53
                    },
                    "coords": {
                        "x": 181,
                        "y": 123,
                        "w": 19,
                        "h": 41
                    }
                },
                {
                    "type": "side",
                    "tile": {
                        "x": 3,
                        "y": -4
                    },
                    "screen": {
                        "x": 19,
                        "y": 53
                    },
                    "coords": {
                        "x": 84,
                        "y": 114,
                        "w": 20,
                        "h": 41
                    }
                },
                {
                    "type": "side",
                    "tile": {
                        "x": 3,
                        "y": -3
                    },
                    "screen": {
                        "x": 0,
                        "y": 50
                    },
                    "coords": {
                        "x": 84,
                        "y": 158,
                        "w": 19,
                        "h": 48
                    }
                }
            ]
        }
    ]
}